[
  {
    "Href": "https://shikimori.one/animes/52991-sousou-no-frieren",
    "Name": "Провожающая в последний путь Фрирен",
    "Type": "TV Сериал",
    "Production year": 2023
  },
  {
    "Href": "https://shikimori.one/animes/z5114-fullmetal-alchemist-brotherhood",
    "Name": "Стальной алхимик: Братство",
    "Type": "TV Сериал",
    "Production year": 2009
  },
  {
    "Href": "https://shikimori.one/animes/z9253-steins-gate",
    "Name": "Врата Штейна",
    "Type": "TV Сериал",
    "Production year": 2011
  },
  {
    "Href": "https://shikimori.one/animes/z28977-gintama",
    "Name": "Гинтама 4",
    "Type": "TV Сериал",
    "Production year": 2015
  },
  {
    "Href": "https://shikimori.one/animes/38524-shingeki-no-kyojin-season-3-part-2",
    "Name": "Атака титанов 3. Часть 2",
    "Type": "TV Сериал",
    "Production year": 2019
  },
  {
    "Href": "https://shikimori.one/animes/41467-bleach-sennen-kessen-hen",
    "Name": "Блич: Тысячелетняя кровавая война",
    "Type": "TV Сериал",
    "Production year": 2022
  },
  {
    "Href": "https://shikimori.one/animes/39486-gintama-the-final",
    "Name": "Гинтама: Финал",
    "Type": "Фильм",
    "Production year": 2021
  },
  {
    "Href": "https://shikimori.one/animes/z11061-hunter-x-hunter-2011",
    "Name": "Охотник х Охотник (2011)",
    "Type": "TV Сериал",
    "Production year": 2011
  },
  {
    "Href": "https://shikimori.one/animes/z9969-gintama",
    "Name": "Гинтама 2",
    "Type": "TV Сериал",
    "Production year": 2011
  },
  {
    "Href": "https://shikimori.one/animes/z15417-gintama-enchousen",
    "Name": "Гинтама 3",
    "Type": "TV Сериал",
    "Production year": 2012
  },
  {
    "Href": "https://shikimori.one/animes/43608-kaguya-sama-wa-kokurasetai-ultra-romantic",
    "Name": "Госпожа Кагуя: в любви как на войне 3",
    "Type": "TV Сериал",
    "Production year": 2022
  },
  {
    "Href": "https://shikimori.one/animes/820-ginga-eiyuu-densetsu",
    "Name": "Легенда о героях Галактики",
    "Type": "OVA",
    "Production year": 1988
  },
  {
    "Href": "https://shikimori.one/animes/820-ginga-eiyuu-densetsu",
    "Name": "Корзинка фруктов: Финал",
    "Type": "TV Сериал",
    "Production year": 2021
  },
  {
    "Href": "https://shikimori.one/animes/z34096-gintama",
    "Name": "Гинтама 5",
    "Type": "TV Сериал",
    "Production year": 2017
  },
  {
    "Href": "https://shikimori.one/animes/51535-shingeki-no-kyojin-the-final-season-kanketsu-hen",
    "Name": "Атака титанов: Финал — Заключительная глава",
    "Type": "Спешл",
    "Production year": 2023
  },
  {
    "Href": "https://shikimori.one/animes/z918-gintama",
    "Name": "Гинтама",
    "Type": "TV Сериал",
    "Production year": 2006
  },
  {
    "Href": "https://shikimori.one/animes/35180-3-gatsu-no-lion-2nd-season",
    "Name": "Мартовский лев 2",
    "Type": "TV Сериал",
    "Production year": 2017
  },
  {
    "Href": "https://shikimori.one/animes/z4181-clannad-after-story",
    "Name": "Кланнад: Продолжение истории",
    "Type": "TV Сериал",
    "Production year": 2008
  },
  {
    "Href": "https://shikimori.one/animes/y28851-koe-no-katachi",
    "Name": "Форма голоса",
    "Type": "Фильм",
    "Production year": 2016
  },
  {
    "Href": "https://shikimori.one/animes/2904-code-geass-hangyaku-no-lelouch-r2",
    "Name": "Код Гиас: Восставший Лелуш 2",
    "Type": "TV Сериал",
    "Production year": 2008
  },
  {
    "Href": "https://shikimori.one/animes/z15335-gintama-movie-2-kanketsu-hen-yorozuya-yo-eien-nare",
    "Name": "Гинтама: Финальная арка — Ёродзуя навсегда!",
    "Type": "Фильм",
    "Production year": 2013
  },
  {
    "Href": "https://shikimori.one/animes/51009-jujutsu-kaisen-2nd-season",
    "Name": "Магическая битва 2",
    "Type": "TV Сериал",
    "Production year": 2023
  },
  {
    "Href": "https://shikimori.one/animes/37491-gintama-shirogane-no-tamashii-hen-kouhan-sen",
    "Name": "Гинтама 8",
    "Type": "TV Сериал",
    "Production year": 2018
  },
  {
    "Href": "https://shikimori.one/animes/19-monster",
    "Name": "Монстр",
    "Type": "TV Сериал",
    "Production year": 2004
  },
  {
    "Href": "https://shikimori.one/animes/z35247-owarimonogatari-2nd-season",
    "Name": "История финала 2",
    "Type": "TV Сериал",
    "Production year": 2017
  },
  {
    "Href": "https://shikimori.one/animes/37987-violet-evergarden-movie",
    "Name": "Вайолет Эвергарден. Фильм",
    "Type": "Фильм",
    "Production year": 2020
  },
  {
    "Href": "https://shikimori.one/animes/32281-kimi-no-na-wa",
    "Name": "Твоё имя",
    "Type": "Фильм",
    "Production year": 2016
  },
  {
    "Href": "https://shikimori.one/animes/40682-kingdom-3rd-season",
    "Name": "Царство 3",
    "Type": "TV Сериал",
    "Production year": 2020
  },
  {
    "Href": "https://shikimori.one/animes/47917-bocchi-the-rock",
    "Name": "Одинокий рокер!",
    "Type": "TV Сериал",
    "Production year": 2022
  },
  {
    "Href": "https://shikimori.one/animes/36838-gintama-shirogane-no-tamashii-hen",
    "Name": "Гинтама 7",
    "Type": "TV Сериал",
    "Production year": 2018
  },
  {
    "Href": "https://shikimori.one/animes/36838-gintama-shirogane-no-tamashii-hen",
    "Name": "Госпожа Кагуя: в любви как на войне — Первый поцелуй никогда не заканчивается",
    "Type": "Фильм",
    "Production year": 2022
  },
  {
    "Href": "https://shikimori.one/animes/45649-the-first-slam-dunk",
    "Name": "Первый слэм-данк",
    "Type": "Фильм",
    "Production year": 2022
  },
  {
    "Href": "https://shikimori.one/animes/49387-vinland-saga-season-2",
    "Name": "Сага о Винланде 2",
    "Type": "TV Сериал",
    "Production year": 2023
  },
  {
    "Href": "https://shikimori.one/animes/z37510-mob-psycho-100-ii",
    "Name": "Моб Психо 100 2",
    "Type": "TV Сериал",
    "Production year": 2019
  },
  {
    "Href": "https://shikimori.one/animes/z31758-kizumonogatari-iii-reiketsu-hen",
    "Name": "Истории ран. Часть 3: Холодная кровь",
    "Type": "Фильм",
    "Production year": 2017
  },
  {
    "Href": "https://shikimori.one/animes/40028-shingeki-no-kyojin-the-final-season",
    "Name": "Атака титанов: Финал",
    "Type": "TV Сериал",
    "Production year": 2020
  },
  {
    "Href": "https://shikimori.one/animes/z199-sen-to-chihiro-no-kamikakushi",
    "Name": "Унесённые призраками",
    "Type": "Фильм",
    "Production year": 2001
  },
  {
    "Href": "https://shikimori.one/animes/z32935-haikyuu-karasuno-koukou-vs-shiratorizawa-gakuen-koukou",
    "Name": "Волейбол!! 3",
    "Type": "TV Сериал",
    "Production year": 2016
  },
  {
    "Href": "https://shikimori.one/animes/263-hajime-no-ippo",
    "Name": "Первый шаг",
    "Type": "TV Сериал",
    "Production year": 2000
  },
  {
    "Href": "https://shikimori.one/animes/47778-kimetsu-no-yaiba-yuukaku-hen",
    "Name": "Клинок, рассекающий демонов: Квартал красных фонарей",
    "Type": "TV Сериал",
    "Production year": 2021
  },
  {
    "Href": "https://shikimori.one/animes/48583-shingeki-no-kyojin-the-final-season-part-2",
    "Name": "Атака титанов: Финал. Часть 2",
    "Type": "TV Сериал",
    "Production year": 2022
  },
  {
    "Href": "https://shikimori.one/animes/x17074-monogatari-series-second-season",
    "Name": "Цикл историй: Второй сезон",
    "Type": "TV Сериал",
    "Production year": 2013
  },
  {
    "Href": "https://shikimori.one/animes/54492-kusuriya-no-hitorigoto",
    "Name": "Монолог фармацевта",
    "Type": "TV Сериал",
    "Production year": 2023
  },
  {
    "Href": "https://shikimori.one/animes/54492-kusuriya-no-hitorigoto",
    "Name": "Сага о Винланде",
    "Type": "TV Сериал",
    "Production year": 2019
  },
  {
    "Href": "https://shikimori.one/animes/1-cowboy-bebop",
    "Name": "Ковбой Бибоп",
    "Type": "TV Сериал",
    "Production year": 1998
  },
  {
    "Href": "https://shikimori.one/animes/50399-tian-guan-cifu-er",
    "Name": "Благословение небожителей 2",
    "Type": "ONA",
    "Production year": 2023
  },
  {
    "Href": "https://shikimori.one/animes/50399-tian-guan-cifu-er",
    "Name": "Мастер муси: Следующая глава 2",
    "Type": "TV Сериал",
    "Production year": 2014
  },
  {
    "Href": "https://shikimori.one/animes/50399-tian-guan-cifu-er",
    "Name": "Царство 4",
    "Type": "TV Сериал",
    "Production year": 2022
  },
  {
    "Href": "https://shikimori.one/animes/52034-oshi-no-ko",
    "Name": "Ребёнок идола",
    "Type": "TV Сериал",
    "Production year": 2023
  },
  {
    "Href": "https://shikimori.one/animes/2921-ashita-no-joe-2",
    "Name": "Завтрашний Джо 2",
    "Type": "TV Сериал",
    "Production year": 1980
  },
  {
    "Href": "https://shikimori.one/animes/2921-ashita-no-joe-2",
    "Name": "Сёва-Гэнроку: Двойное самоубийство по ракуго 2",
    "Type": "TV Сериал",
    "Production year": 2017
  },
  {
    "Href": "https://shikimori.one/animes/53998-bleach-sennen-kessen-hen-ketsubetsu-tan",
    "Name": "Блич: Тысячелетняя кровавая война — Прощание",
    "Type": "TV Сериал",
    "Production year": 2023
  },
  {
    "Href": "https://shikimori.one/animes/50172-mob-psycho-100-iii",
    "Name": "Моб Психо 100 3",
    "Type": "TV Сериал",
    "Production year": 2022
  },
  {
    "Href": "https://shikimori.one/animes/21-one-piece",
    "Name": "Ван-Пис",
    "Type": "TV Сериал",
    "Production year": 1999
  },
  {
    "Href": "https://shikimori.one/animes/21-one-piece",
    "Name": "Бродяга Кэнсин: Воспоминания",
    "Type": "OVA",
    "Production year": 1999
  },
  {
    "Href": "https://shikimori.one/animes/48569-86-part-2",
    "Name": "Восемьдесят шесть. Часть 2",
    "Type": "TV Сериал",
    "Production year": 2021
  },
  {
    "Href": "https://shikimori.one/animes/1575-code-geass-hangyaku-no-lelouch",
    "Name": "Код Гиас: Восставший Лелуш",
    "Type": "TV Сериал",
    "Production year": 2006
  },
  {
    "Href": "https://shikimori.one/animes/245-great-teacher-onizuka",
    "Name": "Крутой учитель Онидзука",
    "Type": "TV Сериал",
    "Production year": 1999
  },
  {
    "Href": "https://shikimori.one/animes/245-great-teacher-onizuka",
    "Name": "Мастер муси: Следующая глава",
    "Type": "TV Сериал",
    "Production year": 2014
  },
  {
    "Href": "https://shikimori.one/animes/45576-mushoku-tensei-isekai-ittara-honki-dasu-part-2",
    "Name": "Реинкарнация безработного: История о приключениях в другом мире. Часть 2",
    "Type": "TV Сериал",
    "Production year": 2021
  }
]