{"file_size": 132900, "file_in_memory_size": 797210.0, "columns_stats": {"h_manager_name": {"total_memory": 10213.0, "memory_space_percentage": 1.28, "dtype": "object"}, "v_manager_name": {"total_memory": 10212.0, "memory_space_percentage": 1.28, "dtype": "object"}, "hp_umpire_name": {"total_memory": 10193.0, "memory_space_percentage": 1.28, "dtype": "object"}, "1b_umpire_name": {"total_memory": 10062.0, "memory_space_percentage": 1.26, "dtype": "object"}, "v_starting_pitcher_name": {"total_memory": 10054.0, "memory_space_percentage": 1.26, "dtype": "object"}, "h_starting_pitcher_name": {"total_memory": 10053.0, "memory_space_percentage": 1.26, "dtype": "object"}, "3b_umpire_name": {"total_memory": 9873.0, "memory_space_percentage": 1.24, "dtype": "object"}, "2b_umpire_name": {"total_memory": 9712.0, "memory_space_percentage": 1.22, "dtype": "object"}, "v_manager_id": {"total_memory": 9569.0, "memory_space_percentage": 1.2, "dtype": "object"}, "h_manager_id": {"total_memory": 9569.0, "memory_space_percentage": 1.2, "dtype": "object"}, "hp_umpire_id": {"total_memory": 9568.0, "memory_space_percentage": 1.2, "dtype": "object"}, "v_starting_pitcher_id": {"total_memory": 9567.0, "memory_space_percentage": 1.2, "dtype": "object"}, "h_starting_pitcher_id": {"total_memory": 9567.0, "memory_space_percentage": 1.2, "dtype": "object"}, "v_player_1_name": {"total_memory": 9371.0, "memory_space_percentage": 1.18, "dtype": "object"}, "h_player_1_name": {"total_memory": 9371.0, "memory_space_percentage": 1.18, "dtype": "object"}, "v_player_7_name": {"total_memory": 9363.0, "memory_space_percentage": 1.17, "dtype": "object"}, "h_player_7_name": {"total_memory": 9362.0, "memory_space_percentage": 1.17, "dtype": "object"}, "v_player_8_name": {"total_memory": 9360.0, "memory_space_percentage": 1.17, "dtype": "object"}, "v_player_2_name": {"total_memory": 9359.0, "memory_space_percentage": 1.17, "dtype": "object"}, "h_player_2_name": {"total_memory": 9359.0, "memory_space_percentage": 1.17, "dtype": "object"}, "h_player_8_name": {"total_memory": 9359.0, "memory_space_percentage": 1.17, "dtype": "object"}, "v_player_3_name": {"total_memory": 9353.0, "memory_space_percentage": 1.17, "dtype": "object"}, "v_player_4_name": {"total_memory": 9353.0, "memory_space_percentage": 1.17, "dtype": "object"}, "h_player_3_name": {"total_memory": 9353.0, "memory_space_percentage": 1.17, "dtype": "object"}, "h_player_4_name": {"total_memory": 9353.0, "memory_space_percentage": 1.17, "dtype": "object"}, "v_player_6_name": {"total_memory": 9351.0, "memory_space_percentage": 1.17, "dtype": "object"}, "h_player_6_name": {"total_memory": 9351.0, "memory_space_percentage": 1.17, "dtype": "object"}, "v_player_9_name": {"total_memory": 9350.0, "memory_space_percentage": 1.17, "dtype": "object"}, "h_player_9_name": {"total_memory": 9350.0, "memory_space_percentage": 1.17, "dtype": "object"}, "v_player_5_name": {"total_memory": 9344.0, "memory_space_percentage": 1.17, "dtype": "object"}, "h_player_5_name": {"total_memory": 9343.0, "memory_space_percentage": 1.17, "dtype": "object"}, "losing_pitcher_name": {"total_memory": 9327.0, "memory_space_percentage": 1.17, "dtype": "object"}, "winning_pitcher_name": {"total_memory": 9326.0, "memory_space_percentage": 1.17, "dtype": "object"}, "lf_umpire_name": {"total_memory": 9234.0, "memory_space_percentage": 1.16, "dtype": "object"}, "rf_umpire_name": {"total_memory": 9233.0, "memory_space_percentage": 1.16, "dtype": "object"}, "winning_rbi_batter_id_name": {"total_memory": 9157.0, "memory_space_percentage": 1.15, "dtype": "object"}, "h_line_score": {"total_memory": 9137.0, "memory_space_percentage": 1.15, "dtype": "object"}, "v_line_score": {"total_memory": 9116.0, "memory_space_percentage": 1.14, "dtype": "object"}, "park_id": {"total_memory": 9065.0, "memory_space_percentage": 1.14, "dtype": "object"}, "1b_umpire_id": {"total_memory": 8961.0, "memory_space_percentage": 1.12, "dtype": "object"}, "saving_pitcher_name": {"total_memory": 8822.0, "memory_space_percentage": 1.11, "dtype": "object"}, "v_player_1_id": {"total_memory": 8810.0, "memory_space_percentage": 1.11, "dtype": "object"}, "v_player_2_id": {"total_memory": 8810.0, "memory_space_percentage": 1.11, "dtype": "object"}, "v_player_3_id": {"total_memory": 8810.0, "memory_space_percentage": 1.11, "dtype": "object"}, "v_player_4_id": {"total_memory": 8810.0, "memory_space_percentage": 1.11, "dtype": "object"}, "v_player_5_id": {"total_memory": 8810.0, "memory_space_percentage": 1.11, "dtype": "object"}, "v_player_6_id": {"total_memory": 8810.0, "memory_space_percentage": 1.11, "dtype": "object"}, "v_player_7_id": {"total_memory": 8810.0, "memory_space_percentage": 1.11, "dtype": "object"}, "v_player_8_id": {"total_memory": 8810.0, "memory_space_percentage": 1.11, "dtype": "object"}, "v_player_9_id": {"total_memory": 8810.0, "memory_space_percentage": 1.11, "dtype": "object"}, "h_player_1_id": {"total_memory": 8810.0, "memory_space_percentage": 1.11, "dtype": "object"}, "h_player_2_id": {"total_memory": 8810.0, "memory_space_percentage": 1.11, "dtype": "object"}, "h_player_3_id": {"total_memory": 8810.0, "memory_space_percentage": 1.11, "dtype": "object"}, "h_player_4_id": {"total_memory": 8810.0, "memory_space_percentage": 1.11, "dtype": "object"}, "h_player_5_id": {"total_memory": 8810.0, "memory_space_percentage": 1.11, "dtype": "object"}, "h_player_6_id": {"total_memory": 8810.0, "memory_space_percentage": 1.11, "dtype": "object"}, "h_player_7_id": {"total_memory": 8810.0, "memory_space_percentage": 1.11, "dtype": "object"}, "h_player_8_id": {"total_memory": 8810.0, "memory_space_percentage": 1.11, "dtype": "object"}, "h_player_9_id": {"total_memory": 8810.0, "memory_space_percentage": 1.11, "dtype": "object"}, "winning_pitcher_id": {"total_memory": 8795.0, "memory_space_percentage": 1.1, "dtype": "object"}, "losing_pitcher_id": {"total_memory": 8795.0, "memory_space_percentage": 1.1, "dtype": "object"}, "day_of_week": {"total_memory": 8729.0, "memory_space_percentage": 1.1, "dtype": "object"}, "v_name": {"total_memory": 8729.0, "memory_space_percentage": 1.1, "dtype": "object"}, "h_name": {"total_memory": 8729.0, "memory_space_percentage": 1.1, "dtype": "object"}, "v_league": {"total_memory": 8561.0, "memory_space_percentage": 1.07, "dtype": "object"}, "h_league": {"total_memory": 8561.0, "memory_space_percentage": 1.07, "dtype": "object"}, "3b_umpire_id": {"total_memory": 8221.0, "memory_space_percentage": 1.03, "dtype": "object"}, "winning_rbi_batter_id": {"total_memory": 7952.0, "memory_space_percentage": 1.0, "dtype": "object"}, "acquisition_info": {"total_memory": 7847.0, "memory_space_percentage": 0.98, "dtype": "object"}, "day_night": {"total_memory": 7835.0, "memory_space_percentage": 0.98, "dtype": "object"}, "2b_umpire_id": {"total_memory": 7533.0, "memory_space_percentage": 0.95, "dtype": "object"}, "saving_pitcher_id": {"total_memory": 6544.0, "memory_space_percentage": 0.82, "dtype": "object"}, "additional_info": {"total_memory": 5417.0, "memory_space_percentage": 0.68, "dtype": "object"}, "lf_umpire_id": {"total_memory": 5377.0, "memory_space_percentage": 0.67, "dtype": "object"}, "completion": {"total_memory": 5375.0, "memory_space_percentage": 0.67, "dtype": "object"}, "protest": {"total_memory": 5375.0, "memory_space_percentage": 0.67, "dtype": "object"}, "forefeit": {"total_memory": 5374.0, "memory_space_percentage": 0.67, "dtype": "object"}, "rf_umpire_id": {"total_memory": 5372.0, "memory_space_percentage": 0.67, "dtype": "object"}, "date": {"total_memory": 1343.0, "memory_space_percentage": 0.17, "dtype": "int64"}, "number_of_game": {"total_memory": 1343.0, "memory_space_percentage": 0.17, "dtype": "int64"}, "v_game_number": {"total_memory": 1343.0, "memory_space_percentage": 0.17, "dtype": "int64"}, "h_game_number": {"total_memory": 1343.0, "memory_space_percentage": 0.17, "dtype": "int64"}, "v_score": {"total_memory": 1343.0, "memory_space_percentage": 0.17, "dtype": "int64"}, "h_score": {"total_memory": 1343.0, "memory_space_percentage": 0.17, "dtype": "int64"}, "length_outs": {"total_memory": 1343.0, "memory_space_percentage": 0.17, "dtype": "float64"}, "attendance": {"total_memory": 1343.0, "memory_space_percentage": 0.17, "dtype": "float64"}, "length_minutes": {"total_memory": 1343.0, "memory_space_percentage": 0.17, "dtype": "float64"}, "v_at_bats": {"total_memory": 1343.0, "memory_space_percentage": 0.17, "dtype": "float64"}, "v_hits": {"total_memory": 1343.0, "memory_space_percentage": 0.17, "dtype": "float64"}, "v_doubles": {"total_memory": 1343.0, "memory_space_percentage": 0.17, "dtype": "float64"}, "v_triples": {"total_memory": 1343.0, "memory_space_percentage": 0.17, "dtype": "float64"}, "v_homeruns": {"total_memory": 1343.0, "memory_space_percentage": 0.17, "dtype": "float64"}, "v_rbi": {"total_memory": 1343.0, "memory_space_percentage": 0.17, "dtype": "float64"}, "v_sacrifice_hits": {"total_memory": 1343.0, "memory_space_percentage": 0.17, "dtype": "float64"}, "v_sacrifice_flies": {"total_memory": 1343.0, "memory_space_percentage": 0.17, "dtype": "float64"}, "v_hit_by_pitch": {"total_memory": 1343.0, "memory_space_percentage": 0.17, "dtype": "float64"}, "v_walks": {"total_memory": 1343.0, "memory_space_percentage": 0.17, "dtype": "float64"}, "v_intentional walks": {"total_memory": 1343.0, "memory_space_percentage": 0.17, "dtype": "float64"}, "v_strikeouts": {"total_memory": 1343.0, "memory_space_percentage": 0.17, "dtype": "float64"}, "v_stolen_bases": {"total_memory": 1343.0, "memory_space_percentage": 0.17, "dtype": "float64"}, "v_caught_stealing": {"total_memory": 1343.0, "memory_space_percentage": 0.17, "dtype": "float64"}, "v_grounded_into_double": {"total_memory": 1343.0, "memory_space_percentage": 0.17, "dtype": "float64"}, "v_first_catcher_interference": {"total_memory": 1343.0, "memory_space_percentage": 0.17, "dtype": "float64"}, "v_left_on_base": {"total_memory": 1343.0, "memory_space_percentage": 0.17, "dtype": "float64"}, "v_pitchers_used": {"total_memory": 1343.0, "memory_space_percentage": 0.17, "dtype": "float64"}, "v_individual_earned_runs": {"total_memory": 1343.0, "memory_space_percentage": 0.17, "dtype": "float64"}, "v_team_earned_runs": {"total_memory": 1343.0, "memory_space_percentage": 0.17, "dtype": "float64"}, "v_wild_pitches": {"total_memory": 1343.0, "memory_space_percentage": 0.17, "dtype": "float64"}, "v_balks": {"total_memory": 1343.0, "memory_space_percentage": 0.17, "dtype": "float64"}, "v_putouts": {"total_memory": 1343.0, "memory_space_percentage": 0.17, "dtype": "float64"}, "v_assists": {"total_memory": 1343.0, "memory_space_percentage": 0.17, "dtype": "float64"}, "v_errors": {"total_memory": 1343.0, "memory_space_percentage": 0.17, "dtype": "float64"}, "v_passed_balls": {"total_memory": 1343.0, "memory_space_percentage": 0.17, "dtype": "float64"}, "v_double_plays": {"total_memory": 1343.0, "memory_space_percentage": 0.17, "dtype": "float64"}, "v_triple_plays": {"total_memory": 1343.0, "memory_space_percentage": 0.17, "dtype": "float64"}, "h_at_bats": {"total_memory": 1343.0, "memory_space_percentage": 0.17, "dtype": "float64"}, "h_hits": {"total_memory": 1343.0, "memory_space_percentage": 0.17, "dtype": "float64"}, "h_doubles": {"total_memory": 1343.0, "memory_space_percentage": 0.17, "dtype": "float64"}, "h_triples": {"total_memory": 1343.0, "memory_space_percentage": 0.17, "dtype": "float64"}, "h_homeruns": {"total_memory": 1343.0, "memory_space_percentage": 0.17, "dtype": "float64"}, "h_rbi": {"total_memory": 1343.0, "memory_space_percentage": 0.17, "dtype": "float64"}, "h_sacrifice_hits": {"total_memory": 1343.0, "memory_space_percentage": 0.17, "dtype": "float64"}, "h_sacrifice_flies": {"total_memory": 1343.0, "memory_space_percentage": 0.17, "dtype": "float64"}, "h_hit_by_pitch": {"total_memory": 1343.0, "memory_space_percentage": 0.17, "dtype": "float64"}, "h_walks": {"total_memory": 1343.0, "memory_space_percentage": 0.17, "dtype": "float64"}, "h_intentional walks": {"total_memory": 1343.0, "memory_space_percentage": 0.17, "dtype": "float64"}, "h_strikeouts": {"total_memory": 1343.0, "memory_space_percentage": 0.17, "dtype": "float64"}, "h_stolen_bases": {"total_memory": 1343.0, "memory_space_percentage": 0.17, "dtype": "float64"}, "h_caught_stealing": {"total_memory": 1343.0, "memory_space_percentage": 0.17, "dtype": "float64"}, "h_grounded_into_double": {"total_memory": 1343.0, "memory_space_percentage": 0.17, "dtype": "float64"}, "h_first_catcher_interference": {"total_memory": 1343.0, "memory_space_percentage": 0.17, "dtype": "float64"}, "h_left_on_base": {"total_memory": 1343.0, "memory_space_percentage": 0.17, "dtype": "float64"}, "h_pitchers_used": {"total_memory": 1343.0, "memory_space_percentage": 0.17, "dtype": "float64"}, "h_individual_earned_runs": {"total_memory": 1343.0, "memory_space_percentage": 0.17, "dtype": "float64"}, "h_team_earned_runs": {"total_memory": 1343.0, "memory_space_percentage": 0.17, "dtype": "float64"}, "h_wild_pitches": {"total_memory": 1343.0, "memory_space_percentage": 0.17, "dtype": "float64"}, "h_balks": {"total_memory": 1343.0, "memory_space_percentage": 0.17, "dtype": "float64"}, "h_putouts": {"total_memory": 1343.0, "memory_space_percentage": 0.17, "dtype": "float64"}, "h_assists": {"total_memory": 1343.0, "memory_space_percentage": 0.17, "dtype": "float64"}, "h_errors": {"total_memory": 1343.0, "memory_space_percentage": 0.17, "dtype": "float64"}, "h_passed_balls": {"total_memory": 1343.0, "memory_space_percentage": 0.17, "dtype": "float64"}, "h_double_plays": {"total_memory": 1343.0, "memory_space_percentage": 0.17, "dtype": "float64"}, "h_triple_plays": {"total_memory": 1343.0, "memory_space_percentage": 0.17, "dtype": "float64"}, "v_player_1_def_pos": {"total_memory": 1343.0, "memory_space_percentage": 0.17, "dtype": "float64"}, "v_player_2_def_pos": {"total_memory": 1343.0, "memory_space_percentage": 0.17, "dtype": "float64"}, "v_player_3_def_pos": {"total_memory": 1343.0, "memory_space_percentage": 0.17, "dtype": "float64"}, "v_player_4_def_pos": {"total_memory": 1343.0, "memory_space_percentage": 0.17, "dtype": "float64"}, "v_player_5_def_pos": {"total_memory": 1343.0, "memory_space_percentage": 0.17, "dtype": "float64"}, "v_player_6_def_pos": {"total_memory": 1343.0, "memory_space_percentage": 0.17, "dtype": "float64"}, "v_player_7_def_pos": {"total_memory": 1343.0, "memory_space_percentage": 0.17, "dtype": "float64"}, "v_player_8_def_pos": {"total_memory": 1343.0, "memory_space_percentage": 0.17, "dtype": "float64"}, "v_player_9_def_pos": {"total_memory": 1343.0, "memory_space_percentage": 0.17, "dtype": "float64"}, "h_player_1_def_pos": {"total_memory": 1343.0, "memory_space_percentage": 0.17, "dtype": "float64"}, "h_player_2_def_pos": {"total_memory": 1343.0, "memory_space_percentage": 0.17, "dtype": "float64"}, "h_player_3_def_pos": {"total_memory": 1343.0, "memory_space_percentage": 0.17, "dtype": "float64"}, "h_player_4_def_pos": {"total_memory": 1343.0, "memory_space_percentage": 0.17, "dtype": "float64"}, "h_player_5_def_pos": {"total_memory": 1343.0, "memory_space_percentage": 0.17, "dtype": "float64"}, "h_player_6_def_pos": {"total_memory": 1343.0, "memory_space_percentage": 0.17, "dtype": "float64"}, "h_player_7_def_pos": {"total_memory": 1343.0, "memory_space_percentage": 0.17, "dtype": "float64"}, "h_player_8_def_pos": {"total_memory": 1343.0, "memory_space_percentage": 0.17, "dtype": "float64"}, "h_player_9_def_pos": {"total_memory": 1343.0, "memory_space_percentage": 0.17, "dtype": "float64"}}}